tidyms/__init__.py
tidyms/_batch_corrector.py
tidyms/_build_data_matrix.py
tidyms/_constants.py
tidyms/_filter_functions.py
tidyms/_mzml.py
tidyms/_plot_bokeh.py
tidyms/assay.py
tidyms/consensus_annotation.py
tidyms/container.py
tidyms/correspondence.py
tidyms/dartms.py
tidyms/fileio.py
tidyms/fill_missing.py
tidyms/filter.py
tidyms/lcms.py
tidyms/peaks.py
tidyms/raw_data_utils.py
tidyms/simulation.py
tidyms/utils.py
tidyms/validation.py
tidyms/annotation/__init__.py
tidyms/annotation/annotation.py
tidyms/annotation/annotation_data.py
tidyms/annotation/envelope_finder.py
tidyms/annotation/mmi_finder.py
tidyms/assay/assay_processor.py
tidyms/chem/__init__.py
tidyms/chem/_envelope_utils.py
tidyms/chem/_formula_generator.py
tidyms/chem/atoms.py
tidyms/chem/elements.json
tidyms/chem/envelope_tools.py
tidyms/chem/formula.py
tidyms/chem/formula_generator_utils.pyx
tidyms/chem/isotope_distribution_utils.pyx
tidyms/chem/isotopes.json
tidyms/chem/utils.py
tidyms-0.7.0.dist-info/METADATA
tidyms-0.7.0.dist-info/WHEEL
tidyms-0.7.0.dist-info/licenses/LICENSE
tidyms-0.7.0.dist-info/RECORD
