Metadata-Version: 2.1
Name: tidyms
Version: 0.7.0
Summary: Tools for working with MS data in metabolomics
Project-URL: Homepage, https://github.com/griquelme/tidyms
Author: Gabriel Riquelme
License: BSD 3-Clause License
License-File: LICENSE
Classifier: License :: OSI Approved :: BSD License
Classifier: Programming Language :: Python :: 3.9
Classifier: Programming Language :: Python :: 3.10
Classifier: Topic :: Scientific/Engineering :: Bio-Informatics
Classifier: Topic :: Scientific/Engineering :: Chemistry
Classifier: Topic :: Scientific/Engineering :: Medical Science Apps.
Requires-Python: >=3.9
Requires-Dist: beautifulsoup4>=4.11.2
Requires-Dist: bokeh>=3.0
Requires-Dist: cerberus>=1.3
Requires-Dist: dill>=0.3.6
Requires-Dist: ipython>=8.1
Requires-Dist: joblib>=1.1
Requires-Dist: matplotlib>=3.5.1
Requires-Dist: natsort>=8.2.0
Requires-Dist: networkx>=3.0
Requires-Dist: numpy>=1.22
Requires-Dist: openpyxl>=3.0
Requires-Dist: pandas>=1.5.3
Requires-Dist: plotnine>=0.10.1
Requires-Dist: requests
Requires-Dist: scikit-learn>=1.0.2
Requires-Dist: scipy>=1.8
Requires-Dist: seaborn>=0.11
Requires-Dist: statsmodels>=0.13
Requires-Dist: tqdm>=4.0
Requires-Dist: umap-learn>=0.5.3
Requires-Dist: xlrd>=2.0
